{"_id":"nub","_rev":"3-932ecf56889fa43584687dbb2cf4aa91","name":"nub","description":"Uniqueness functions","dist-tags":{"latest":"0.0.0"},"versions":{"0.0.0":{"name":"nub","version":"0.0.0","description":"Uniqueness functions","main":"index.js","directories":{"lib":".","example":"example","test":"test"},"dependencies":{},"devDependencies":{"expresso":"0.7.x"},"scripts":{"test":"expresso"},"repository":{"type":"git","url":"git://github.com/substack/node-nub.git"},"keywords":["unique","uniq","uniqBy","nub","nubBy"],"author":{"name":"James Halliday","email":"mail@substack.net","url":"http://substack.net"},"license":"MIT/X11","engine":{"node":">=0.4"},"_id":"nub@0.0.0","engines":{"node":"*"},"_engineSupported":true,"_npmVersion":"1.0.10","_nodeVersion":"v0.5.0-pre","_defaultsLoaded":true,"dist":{"shasum":"b369bd32bdde66af59605c3b0520bc219dccc04f","tarball":"http://registry.npmjs.org/nub/-/nub-0.0.0.tgz"}}},"maintainers":[{"name":"substack","email":"mail@substack.net"}],"time":{"0.0.0":"2011-06-25T03:48:56.578Z"},"author":{"name":"James Halliday","email":"mail@substack.net","url":"http://substack.net"},"repository":{"type":"git","url":"git://github.com/substack/node-nub.git"},"_attachments":{},"_etag":"\"8YMHMP11JX4ZWM176KII4WKN\""}